MANIFEST.in
README
requirements.txt
run.py
set_hosts.py
setup.py
Souma.egg-info/PKG-INFO
Souma.egg-info/SOURCES.txt
Souma.egg-info/dependency_links.txt
Souma.egg-info/requires.txt
Souma.egg-info/top_level.txt
astrolab/__init__.py
astrolab/helpers.py
astrolab/interestmodel.py
astrolab/topicmodel.py
nucleus/__init__.py
nucleus/models.py
nucleus/vesicle.py
static/favicon.png
static/css/bootstrap-responsive.css
static/css/bootstrap.css
static/css/frameless.css
static/css/frameless.less
static/css/jasny-bootstrap.css
static/css/main.css
static/css/main.less
static/css/reset.css
static/font-awesome/css/font-awesome.css
static/font-awesome/css/font-awesome.min.css
static/font-awesome/fonts/FontAwesome.otf
static/font-awesome/fonts/fontawesome-webfont.eot
static/font-awesome/fonts/fontawesome-webfont.svg
static/font-awesome/fonts/fontawesome-webfont.ttf
static/font-awesome/fonts/fontawesome-webfont.woff
static/font-awesome/less/bordered-pulled.less
static/font-awesome/less/core.less
static/font-awesome/less/fixed-width.less
static/font-awesome/less/font-awesome.less
static/font-awesome/less/icons.less
static/font-awesome/less/larger.less
static/font-awesome/less/list.less
static/font-awesome/less/mixins.less
static/font-awesome/less/path.less
static/font-awesome/less/rotated-flipped.less
static/font-awesome/less/spinning.less
static/font-awesome/less/stacked.less
static/font-awesome/less/variables.less
static/font-awesome/scss/_bordered-pulled.scss
static/font-awesome/scss/_core.scss
static/font-awesome/scss/_fixed-width.scss
static/font-awesome/scss/_icons.scss
static/font-awesome/scss/_larger.scss
static/font-awesome/scss/_list.scss
static/font-awesome/scss/_mixins.scss
static/font-awesome/scss/_path.scss
static/font-awesome/scss/_rotated-flipped.scss
static/font-awesome/scss/_spinning.scss
static/font-awesome/scss/_stacked.scss
static/font-awesome/scss/_variables.scss
static/font-awesome/scss/font-awesome.scss
static/fonts/delicious-opentype/Delicious-Bold.otf
static/fonts/delicious-opentype/Delicious-BoldItalic.otf
static/fonts/delicious-opentype/Delicious-Heavy.otf
