Metadata-Version: 1.0
Name: Souma
Version: 0.2.1
Summary: A Cognitive Network for Groups
Home-page: https://github.com/ciex/souma/
Author: Cognitive Networks Group
Author-email: cognitive-networks@googlegroups.com
License: Apache License 2.0
Platform: UNKNOWN
